{
  "authors": [
    {
      "'{affiliation:Oran}'": "",
      "id": 1
    },
    {
      "id": 2,
      "INSPIRE_number": "INSPIRE_3",
      "affiliation": "Cormoran",
      "name": {
        "first_name": "Keisha",
        "last_name": "Rice"
      },
      "title": "Forbell Street"
    },
    {
      "id": 3,
      "INSPIRE_number": "INSPIRE_6",
      "affiliation": "Scentric",
      "name": {
        "first_name": "Lenora",
        "last_name": "Dixon"
      },
      "title": "Rock Street"
    },
    {
      "id": 4,
      "INSPIRE_number": "INSPIRE_10",
      "affiliation": "Insectus",
      "name": {
        "first_name": "Tate",
        "last_name": "Rose"
      },
      "title": "Bills Place"
    },
    {
      "id": 5,
      "INSPIRE_number": "INSPIRE_1",
      "affiliation": "Playce",
      "name": {
        "first_name": "Frankie",
        "last_name": "Benton"
      },
      "title": "Moultrie Street"
    },
    {
      "id": 6,
      "INSPIRE_number": "INSPIRE_7",
      "affiliation": "Fibrodyne",
      "name": {
        "first_name": "Jacquelyn",
        "last_name": "Massey"
      },
      "title": "Ellery Street"
    },
    {
      "id": 7,
      "INSPIRE_number": "INSPIRE_3",
      "affiliation": "Enthaze",
      "name": {
        "first_name": "Harrison",
        "last_name": "Castaneda"
      },
      "title": "Elliott Place"
    },
    {
      "id": 8,
      "INSPIRE_number": "INSPIRE_8",
      "affiliation": "Opticom",
      "name": {
        "first_name": "Gladys",
        "last_name": "Suarez"
      },
      "title": "Aurelia Court"
    },
    {
      "id": 9,
      "INSPIRE_number": "INSPIRE_10",
      "affiliation": "Maroptic",
      "name": {
        "first_name": "Evelyn",
        "last_name": "Cook"
      },
      "title": "Bayview Place"
    },
    {
      "id": 10,
      "INSPIRE_number": "INSPIRE_0",
      "affiliation": "Microluxe",
      "name": {
        "first_name": "Macias",
        "last_name": "Dickerson"
      },
      "title": "Sackett Street"
    },
    {
      "id": 11,
      "INSPIRE_number": "INSPIRE_9",
      "affiliation": "Norsul",
      "name": {
        "first_name": "Estes",
        "last_name": "Solis"
      },
      "title": "Aviation Road"
    },
    {
      "id": 12,
      "INSPIRE_number": "INSPIRE_10",
      "affiliation": "Xeronk",
      "name": {
        "first_name": "Loretta",
        "last_name": "Beck"
      },
      "title": "Himrod Street"
    },
    {
      "id": 13,
      "INSPIRE_number": "INSPIRE_2",
      "affiliation": "Eweville",
      "name": {
        "first_name": "Candice",
        "last_name": "Cash"
      },
      "title": "Sullivan Place"
    },
    {
      "id": 14,
      "INSPIRE_number": "INSPIRE_0",
      "affiliation": "Yogasm",
      "name": {
        "first_name": "Hallie",
        "last_name": "Frye"
      },
      "title": "Crawford Avenue"
    },
    {
      "id": 15,
      "INSPIRE_number": "INSPIRE_2",
      "affiliation": "Bitendrex",
      "name": {
        "first_name": "Jenifer",
        "last_name": "Gray"
      },
      "title": "Gardner Avenue"
    },
    {
      "id": 16,
      "INSPIRE_number": "INSPIRE_8",
      "affiliation": "Pulze",
      "name": {
        "first_name": "Monica",
        "last_name": "Burns"
      },
      "title": "Nelson Street"
    },
    {
      "id": 17,
      "INSPIRE_number": "INSPIRE_6",
      "affiliation": "Renovize",
      "name": {
        "first_name": "Oliver",
        "last_name": "Reed"
      },
      "title": "Montrose Avenue"
    },
    {
      "id": 18,
      "INSPIRE_number": "INSPIRE_10",
      "affiliation": "Kiggle",
      "name": {
        "first_name": "Webb",
        "last_name": "Slater"
      },
      "title": "Arion Place"
    },
    {
      "id": 19,
      "INSPIRE_number": "INSPIRE_5",
      "affiliation": "Intrawear",
      "name": {
        "first_name": "Noel",
        "last_name": "Cantrell"
      },
      "title": "Bath Avenue"
    },
    {
      "id": 20,
      "INSPIRE_number": "INSPIRE_5",
      "affiliation": "Ovium",
      "name": {
        "first_name": "Stacey",
        "last_name": "Robles"
      },
      "title": "Lenox Road"
    },
    {
      "id": 21,
      "INSPIRE_number": "INSPIRE_6",
      "affiliation": "Dognost",
      "name": {
        "first_name": "Pansy",
        "last_name": "Moon"
      },
      "title": "Jefferson Street"
    },
    {
      "id": 22,
      "INSPIRE_number": "INSPIRE_6",
      "affiliation": "Duflex",
      "name": {
        "first_name": "Hodge",
        "last_name": "Burgess"
      },
      "title": "Plymouth Street"
    },
    {
      "id": 23,
      "INSPIRE_number": "INSPIRE_2",
      "affiliation": "Peticular",
      "name": {
        "first_name": "Richards",
        "last_name": "Bean"
      },
      "title": "Chester Street"
    },
    {
      "id": 24,
      "INSPIRE_number": "INSPIRE_6",
      "affiliation": "Updat",
      "name": {
        "first_name": "Traci",
        "last_name": "Saunders"
      },
      "title": "Landis Court"
    },
    {
      "id": 25,
      "INSPIRE_number": "INSPIRE_6",
      "affiliation": "Tubesys",
      "name": {
        "first_name": "Aurora",
        "last_name": "Rodriquez"
      },
      "title": "Albee Square"
    },
    {
      "id": 26,
      "INSPIRE_number": "INSPIRE_5",
      "affiliation": "Songlines",
      "name": {
        "first_name": "Vance",
        "last_name": "Wilkins"
      },
      "title": "Devon Avenue"
    },
    {
      "id": 27,
      "INSPIRE_number": "INSPIRE_0",
      "affiliation": "Katakana",
      "name": {
        "first_name": "Lorraine",
        "last_name": "Middleton"
      },
      "title": "Beadel Street"
    },
    {
      "id": 28,
      "INSPIRE_number": "INSPIRE_9",
      "affiliation": "Zillan",
      "name": {
        "first_name": "Snider",
        "last_name": "Cotton"
      },
      "title": "Dare Court"
    },
    {
      "id": 29,
      "INSPIRE_number": "INSPIRE_0",
      "affiliation": "Jetsilk",
      "name": {
        "first_name": "Edwards",
        "last_name": "Hodge"
      },
      "title": "Portland Avenue"
    },
    {
      "id": 30,
      "INSPIRE_number": "INSPIRE_4",
      "affiliation": "Marqet",
      "name": {
        "first_name": "Chaney",
        "last_name": "Roberts"
      },
      "title": "Onderdonk Avenue"
    },
    {
      "id": 31,
      "INSPIRE_number": "INSPIRE_7",
      "affiliation": "Honotron",
      "name": {
        "first_name": "Roseann",
        "last_name": "Stuart"
      },
      "title": "Jewel Street"
    },
    {
      "id": 32,
      "INSPIRE_number": "INSPIRE_4",
      "affiliation": "Nimon",
      "name": {
        "first_name": "Conner",
        "last_name": "Stafford"
      },
      "title": "Court Street"
    },
    {
      "id": 33,
      "INSPIRE_number": "INSPIRE_5",
      "affiliation": "Fishland",
      "name": {
        "first_name": "Dolly",
        "last_name": "Colon"
      },
      "title": "Bay Street"
    },
    {
      "id": 34,
      "INSPIRE_number": "INSPIRE_10",
      "affiliation": "Comtours",
      "name": {
        "first_name": "Summers",
        "last_name": "Reid"
      },
      "title": "Hunts Lane"
    },
    {
      "id": 35,
      "INSPIRE_number": "INSPIRE_5",
      "affiliation": "Andershun",
      "name": {
        "first_name": "Christie",
        "last_name": "Huber"
      },
      "title": "Richards Street"
    },
    {
      "id": 36,
      "INSPIRE_number": "INSPIRE_9",
      "affiliation": "Zentility",
      "name": {
        "first_name": "Corinne",
        "last_name": "Bradshaw"
      },
      "title": "Clermont Avenue"
    },
    {
      "id": 37,
      "INSPIRE_number": "INSPIRE_0",
      "affiliation": "Miraclis",
      "name": {
        "first_name": "Hudson",
        "last_name": "Guthrie"
      },
      "title": "Lake Avenue"
    },
    {
      "id": 38,
      "INSPIRE_number": "INSPIRE_0",
      "affiliation": "Manufact",
      "name": {
        "first_name": "Sheila",
        "last_name": "Bass"
      },
      "title": "Cameron Court"
    },
    {
      "id": 39,
      "INSPIRE_number": "INSPIRE_1",
      "affiliation": "Flexigen",
      "name": {
        "first_name": "Greer",
        "last_name": "Mcguire"
      },
      "title": "Mayfair Drive"
    },
    {
      "id": 40,
      "INSPIRE_number": "INSPIRE_1",
      "affiliation": "Jasper",
      "name": {
        "first_name": "Graves",
        "last_name": "Stanley"
      },
      "title": "Hubbard Place"
    },
    {
      "id": 41,
      "INSPIRE_number": "INSPIRE_6",
      "affiliation": "Infotrips",
      "name": {
        "first_name": "Reva",
        "last_name": "Marquez"
      },
      "title": "Dorset Street"
    },
    {
      "id": 42,
      "INSPIRE_number": "INSPIRE_3",
      "affiliation": "Bostonic",
      "name": {
        "first_name": "Campbell",
        "last_name": "Mejia"
      },
      "title": "Chapel Street"
    },
    {
      "id": 43,
      "INSPIRE_number": "INSPIRE_4",
      "affiliation": "Earthplex",
      "name": {
        "first_name": "Mccullough",
        "last_name": "Pratt"
      },
      "title": "Amboy Street"
    },
    {
      "id": 44,
      "INSPIRE_number": "INSPIRE_9",
      "affiliation": "Goko",
      "name": {
        "first_name": "Melissa",
        "last_name": "Ballard"
      },
      "title": "Stratford Road"
    },
    {
      "id": 45,
      "INSPIRE_number": "INSPIRE_4",
      "affiliation": "Sunclipse",
      "name": {
        "first_name": "Barber",
        "last_name": "Carrillo"
      },
      "title": "Sheffield Avenue"
    },
    {
      "id": 46,
      "INSPIRE_number": "INSPIRE_6",
      "affiliation": "Accuprint",
      "name": {
        "first_name": "Tamra",
        "last_name": "Marks"
      },
      "title": "Horace Court"
    },
    {
      "id": 47,
      "INSPIRE_number": "INSPIRE_8",
      "affiliation": "Slax",
      "name": {
        "first_name": "Abby",
        "last_name": "Crane"
      },
      "title": "Langham Street"
    },
    {
      "id": 48,
      "INSPIRE_number": "INSPIRE_0",
      "affiliation": "Junipoor",
      "name": {
        "first_name": "Cleo",
        "last_name": "Joseph"
      },
      "title": "Cove Lane"
    },
    {
      "id": 49,
      "INSPIRE_number": "INSPIRE_10",
      "affiliation": "Bugsall",
      "name": {
        "first_name": "Caroline",
        "last_name": "Carr"
      },
      "title": "Abbey Court"
    },
    {
      "id": 50,
      "INSPIRE_number": "INSPIRE_3",
      "affiliation": "Accufarm",
      "name": {
        "first_name": "Short",
        "last_name": "Klein"
      },
      "title": "Hancock Street"
    },
    {
      "id": 51,
      "INSPIRE_number": "INSPIRE_5",
      "affiliation": "Bisba",
      "name": {
        "first_name": "Jamie",
        "last_name": "York"
      },
      "title": "Johnson Street"
    },
    {
      "id": 52,
      "INSPIRE_number": "INSPIRE_2",
      "affiliation": "Exodoc",
      "name": {
        "first_name": "Kate",
        "last_name": "Odonnell"
      },
      "title": "Richardson Street"
    },
    {
      "id": 53,
      "INSPIRE_number": "INSPIRE_9",
      "affiliation": "Vertide",
      "name": {
        "first_name": "Pitts",
        "last_name": "Schultz"
      },
      "title": "Poplar Avenue"
    },
    {
      "id": 54,
      "INSPIRE_number": "INSPIRE_2",
      "affiliation": "Lumbrex",
      "name": {
        "first_name": "Alyson",
        "last_name": "Kirby"
      },
      "title": "Beach Place"
    },
    {
      "id": 55,
      "INSPIRE_number": "INSPIRE_1",
      "affiliation": "Pyramia",
      "name": {
        "first_name": "Irwin",
        "last_name": "Frost"
      },
      "title": "Banner Avenue"
    },
    {
      "id": 56,
      "INSPIRE_number": "INSPIRE_6",
      "affiliation": "Globoil",
      "name": {
        "first_name": "Snyder",
        "last_name": "Mcclain"
      },
      "title": "Cheever Place"
    },
    {
      "id": 57,
      "INSPIRE_number": "INSPIRE_10",
      "affiliation": "Bolax",
      "name": {
        "first_name": "Georgia",
        "last_name": "Sloan"
      },
      "title": "Melrose Street"
    },
    {
      "id": 58,
      "INSPIRE_number": "INSPIRE_7",
      "affiliation": "Otherside",
      "name": {
        "first_name": "Kristin",
        "last_name": "Herring"
      },
      "title": "Homecrest Avenue"
    },
    {
      "id": 59,
      "INSPIRE_number": "INSPIRE_3",
      "affiliation": "Incubus",
      "name": {
        "first_name": "Norton",
        "last_name": "Mckay"
      },
      "title": "Brooklyn Road"
    },
    {
      "id": 60,
      "INSPIRE_number": "INSPIRE_8",
      "affiliation": "Xymonk",
      "name": {
        "first_name": "Wagner",
        "last_name": "Mayo"
      },
      "title": "Legion Street"
    },
    {
      "id": 61,
      "INSPIRE_number": "INSPIRE_3",
      "affiliation": "Slumberia",
      "name": {
        "first_name": "Dorothy",
        "last_name": "Zimmerman"
      },
      "title": "Oceanview Avenue"
    },
    {
      "id": 62,
      "INSPIRE_number": "INSPIRE_8",
      "affiliation": "Eclipsent",
      "name": {
        "first_name": "Leslie",
        "last_name": "Gould"
      },
      "title": "Seba Avenue"
    },
    {
      "id": 63,
      "INSPIRE_number": "INSPIRE_0",
      "affiliation": "Zolar",
      "name": {
        "first_name": "Brianna",
        "last_name": "Santana"
      },
      "title": "Jerome Avenue"
    },
    {
      "id": 64,
      "INSPIRE_number": "INSPIRE_4",
      "affiliation": "Geoform",
      "name": {
        "first_name": "Curtis",
        "last_name": "Mcconnell"
      },
      "title": "Kermit Place"
    },
    {
      "id": 65,
      "INSPIRE_number": "INSPIRE_3",
      "affiliation": "Enervate",
      "name": {
        "first_name": "Mcgowan",
        "last_name": "Jacobs"
      },
      "title": "Jay Street"
    },
    {
      "id": 66,
      "INSPIRE_number": "INSPIRE_0",
      "affiliation": "Terragen",
      "name": {
        "first_name": "Beverly",
        "last_name": "Goodman"
      },
      "title": "Hutchinson Court"
    },
    {
      "id": 67,
      "INSPIRE_number": "INSPIRE_4",
      "affiliation": "Olympix",
      "name": {
        "first_name": "Lawrence",
        "last_name": "Moreno"
      },
      "title": "Balfour Place"
    },
    {
      "id": 68,
      "INSPIRE_number": "INSPIRE_3",
      "affiliation": "Arctiq",
      "name": {
        "first_name": "Erin",
        "last_name": "Wood"
      },
      "title": "Walker Court"
    },
    {
      "id": 69,
      "INSPIRE_number": "INSPIRE_10",
      "affiliation": "Petigems",
      "name": {
        "first_name": "Russell",
        "last_name": "Dyer"
      },
      "title": "Denton Place"
    },
    {
      "id": 70,
      "INSPIRE_number": "INSPIRE_9",
      "affiliation": "Gaptec",
      "name": {
        "first_name": "Daugherty",
        "last_name": "Ferguson"
      },
      "title": "Hinsdale Street"
    },
    {
      "id": 71,
      "INSPIRE_number": "INSPIRE_3",
      "affiliation": "Fuelton",
      "name": {
        "first_name": "Pauline",
        "last_name": "Hatfield"
      },
      "title": "Irving Place"
    },
    {
      "id": 72,
      "INSPIRE_number": "INSPIRE_2",
      "affiliation": "Bizmatic",
      "name": {
        "first_name": "Benton",
        "last_name": "Sims"
      },
      "title": "Stuyvesant Avenue"
    },
    {
      "id": 73,
      "INSPIRE_number": "INSPIRE_5",
      "affiliation": "Dymi",
      "name": {
        "first_name": "Blevins",
        "last_name": "Waters"
      },
      "title": "Butler Place"
    },
    {
      "id": 74,
      "INSPIRE_number": "INSPIRE_10",
      "affiliation": "Papricut",
      "name": {
        "first_name": "Peterson",
        "last_name": "Mcclure"
      },
      "title": "Sumpter Street"
    },
    {
      "id": 75,
      "INSPIRE_number": "INSPIRE_10",
      "affiliation": "Quarex",
      "name": {
        "first_name": "Franks",
        "last_name": "Lawson"
      },
      "title": "Stryker Street"
    },
    {
      "id": 76,
      "INSPIRE_number": "INSPIRE_1",
      "affiliation": "Genmom",
      "name": {
        "first_name": "Jennings",
        "last_name": "Webster"
      },
      "title": "Hudson Avenue"
    },
    {
      "id": 77,
      "INSPIRE_number": "INSPIRE_6",
      "affiliation": "Exoswitch",
      "name": {
        "first_name": "Valencia",
        "last_name": "Hester"
      },
      "title": "Bevy Court"
    },
    {
      "id": 78,
      "INSPIRE_number": "INSPIRE_6",
      "affiliation": "Neteria",
      "name": {
        "first_name": "Larsen",
        "last_name": "Romero"
      },
      "title": "Vanderbilt Avenue"
    },
    {
      "id": 79,
      "INSPIRE_number": "INSPIRE_6",
      "affiliation": "Oatfarm",
      "name": {
        "first_name": "Florence",
        "last_name": "Santiago"
      },
      "title": "Henry Street"
    },
    {
      "id": 80,
      "INSPIRE_number": "INSPIRE_9",
      "affiliation": "Furnitech",
      "name": {
        "first_name": "Penny",
        "last_name": "Mccoy"
      },
      "title": "Alice Court"
    },
    {
      "id": 81,
      "INSPIRE_number": "INSPIRE_5",
      "affiliation": "Rocklogic",
      "name": {
        "first_name": "Corine",
        "last_name": "Hyde"
      },
      "title": "Gaylord Drive"
    },
    {
      "id": 82,
      "INSPIRE_number": "INSPIRE_1",
      "affiliation": "Enersave",
      "name": {
        "first_name": "Montgomery",
        "last_name": "Bray"
      },
      "title": "Benson Avenue"
    },
    {
      "id": 83,
      "INSPIRE_number": "INSPIRE_10",
      "affiliation": "Kengen",
      "name": {
        "first_name": "Alberta",
        "last_name": "Larsen"
      },
      "title": "Bainbridge Street"
    },
    {
      "id": 84,
      "INSPIRE_number": "INSPIRE_6",
      "affiliation": "Rodemco",
      "name": {
        "first_name": "Nita",
        "last_name": "Wong"
      },
      "title": "Beacon Court"
    },
    {
      "id": 85,
      "INSPIRE_number": "INSPIRE_0",
      "affiliation": "Metroz",
      "name": {
        "first_name": "Sanford",
        "last_name": "Jennings"
      },
      "title": "Metrotech Courtr"
    },
    {
      "id": 86,
      "INSPIRE_number": "INSPIRE_3",
      "affiliation": "Interfind",
      "name": {
        "first_name": "Calhoun",
        "last_name": "Combs"
      },
      "title": "Fanchon Place"
    },
    {
      "id": 87,
      "INSPIRE_number": "INSPIRE_5",
      "affiliation": "Ovolo",
      "name": {
        "first_name": "Garcia",
        "last_name": "Sawyer"
      },
      "title": "Perry Terrace"
    },
    {
      "id": 88,
      "INSPIRE_number": "INSPIRE_3",
      "affiliation": "Prosely",
      "name": {
        "first_name": "Roberson",
        "last_name": "Lambert"
      },
      "title": "Jodie Court"
    },
    {
      "id": 89,
      "INSPIRE_number": "INSPIRE_6",
      "affiliation": "Fangold",
      "name": {
        "first_name": "Odessa",
        "last_name": "Petty"
      },
      "title": "Heath Place"
    },
    {
      "id": 90,
      "INSPIRE_number": "INSPIRE_2",
      "affiliation": "Freakin",
      "name": {
        "first_name": "Kennedy",
        "last_name": "Hoffman"
      },
      "title": "Corbin Place"
    },
    {
      "id": 91,
      "INSPIRE_number": "INSPIRE_1",
      "affiliation": "Columella",
      "name": {
        "first_name": "Dina",
        "last_name": "Hunter"
      },
      "title": "Leonora Court"
    },
    {
      "id": 92,
      "INSPIRE_number": "INSPIRE_1",
      "affiliation": "Paprikut",
      "name": {
        "first_name": "Debra",
        "last_name": "Leach"
      },
      "title": "Halleck Street"
    },
    {
      "id": 93,
      "INSPIRE_number": "INSPIRE_6",
      "affiliation": "Comdom",
      "name": {
        "first_name": "Opal",
        "last_name": "Bridges"
      },
      "title": "Otsego Street"
    },
    {
      "id": 94,
      "INSPIRE_number": "INSPIRE_4",
      "affiliation": "Xylar",
      "name": {
        "first_name": "Cochran",
        "last_name": "Phillips"
      },
      "title": "Malbone Street"
    },
    {
      "id": 95,
      "INSPIRE_number": "INSPIRE_1",
      "affiliation": "Intradisk",
      "name": {
        "first_name": "Dalton",
        "last_name": "Franks"
      },
      "title": "Eaton Court"
    },
    {
      "id": 96,
      "INSPIRE_number": "INSPIRE_2",
      "affiliation": "Equitox",
      "name": {
        "first_name": "Cantu",
        "last_name": "Wall"
      },
      "title": "Bergen Place"
    },
    {
      "id": 97,
      "INSPIRE_number": "INSPIRE_8",
      "affiliation": "Ohmnet",
      "name": {
        "first_name": "Elisabeth",
        "last_name": "Cherry"
      },
      "title": "Lynch Street"
    },
    {
      "id": 98,
      "INSPIRE_number": "INSPIRE_10",
      "affiliation": "Turnabout",
      "name": {
        "first_name": "Reynolds",
        "last_name": "Beach"
      },
      "title": "Emerald Street"
    },
    {
      "id": 99,
      "INSPIRE_number": "INSPIRE_9",
      "affiliation": "Supremia",
      "name": {
        "first_name": "Annie",
        "last_name": "Silva"
      },
      "title": "Dictum Court"
    },
    {
      "id": 100,
      "INSPIRE_number": "INSPIRE_8",
      "affiliation": "Inrt",
      "name": {
        "first_name": "Harriett",
        "last_name": "Reilly"
      },
      "title": "Gallatin Place"
    }
  ]
}